shuffleify/__init__.py
shuffleify/core.py
shuffleify/shuffler.py
shuffleify-1.0.0.dist-info/LICENSE.txt
shuffleify-1.0.0.dist-info/METADATA
shuffleify-1.0.0.dist-info/WHEEL
shuffleify-1.0.0.dist-info/top_level.txt
shuffleify-1.0.0.dist-info/RECORD
