Metadata-Version: 2.1
Name: shuffleify
Version: 1.0.0
Summary: Spotify Shuffle Assistant
Author: iamalreadynoob
Author-email: <sadikefe69@gmail.com>
Keywords: python,spotify,shuffling
Classifier: Development Status :: 1 - Planning
Classifier: Intended Audience :: Developers
Classifier: Programming Language :: Python :: 3
Classifier: Operating System :: Unix
Classifier: Operating System :: MacOS :: MacOS X
Classifier: Operating System :: Microsoft :: Windows
License-File: LICENSE.txt
Requires-Dist: spotipy
